[
	{
	"id": 0,
	"name": "Sophie Vågsæther",
	"age": "25",
	"url": "http://lol.tv3.no/julius",
	"sex": [],
	"notsex": [],
	"picture": "/img/sophie.png"
}, {
	"id": 1,
	"name": "Martine Johansen",
	"age": "21",
	"url": "http://lol.tv3.no/kornelius",
	"sex": [],
	"notsex": [],
	"picture": "/img/martine.png"
}, {
	"id": 2,
	"name": "Aleksander Sæterstøl",
	"age": "23",
	"url": "http://lol.tv3.no/kornelius",
	"sex": [],
	"notsex": [],
	"picture": "/img/aleksander.png"
}, {
	"id": 3,
	"name": "Grunde Myhrer",
	"age": "20",
	"url": "http://lol.tv3.no/kornelius",
	"sex": [],
	"notsex": [],
	"picture": "/img/grunde.png"
	},
	{
	"id": 4,
	"name": "Rebecca Forsbæck",
	"age": "23",
	"url": "http://lol.tv3.no/kornelius",
	"sex": [],
	"notsex": [],
	"picture": "/img/rebecca.png"
	},
	{
	"id": 5,
	"name": "Andrea Sveinsdottir",
	"age": "23",
	"url": "http://lol.tv3.no/kornelius",
	"sex": [],
	"notsex": [],
	"picture": "/img/andrea.png"
	},
	{
	"id": 6,
	"name": "Sofie Nilsen",
	"age": "23",
	"url": "http://lol.tv3.no/kornelius",
	"sex": [],
	"notsex": [],
	"picture": "/img/sofie.png"
	},
	{
		"id": 7,
		"name": "Haakon Gulla Pedersen",
		"age": "23",
		"url": "http://lol.tv3.no/kornelius",
		"sex": [],
		"notsex": [],
		"picture": "/img/haakon.png"
	},
	{
		"id": 8,
		"name": "Morten Monsen Botten",
		"age": "23",
		"url": "http://lol.tv3.no/kornelius",
		"sex": [],
		"notsex": [],
		"picture": "/img/morten.png"
	},
	{
		"id": 9,
		"name": "Kevin René Gustavsson",
		"age": "23",
		"url": "http://lol.tv3.no/kornelius",
		"sex": [],
		"notsex": [],
		"picture": "/img/kevin.png"
	},
	{
		"id": 10,
		"name": "Joachim Solvang",
		"age": "26",
		"url": "http://lol.tv3.no/kornelius",
		"sex": [],
		"notsex": [],
		"picture": "/img/joachim.png"
	},
	{
		"id": 11,
		"name": "Jonas Andersen",
		"age": "26",
		"url": "http://lol.tv3.no/kornelius",
		"sex": [],
		"notsex": [],
		"picture": "/img/jonas.png"
	},
	{
		"id": 12,
		"name": "Mathias Haugsdal",
		"age": "26",
		"url": "http://lol.tv3.no/kornelius",
		"sex": [],
		"notsex": [],
		"picture": "/img/mathias.png"
	},
	{
		"id": 13,
		"name": "Marcus Borger",
		"age": "26",
		"url": "http://lol.tv3.no/kornelius",
		"sex": [],
		"notsex": [],
		"picture": "/img/marcus.png"
	},
	{
		"id": 14,
		"name": "Petter Sjurseth Berg",
		"age": "26",
		"url": "http://lol.tv3.no/kornelius",
		"sex": [],
		"notsex": [],
		"picture": "/img/petter.png"
	}
]
